DinarLib/__init__.py
DinarLib/intersec.py
DinarLib/quick_sort.py
DinarLib/random_sum_to.py
dinarlib-0.0.2.dist-info/METADATA
dinarlib-0.0.2.dist-info/WHEEL
dinarlib-0.0.2.dist-info/top_level.txt
dinarlib-0.0.2.dist-info/RECORD
