Metadata-Version: 2.1
Name: dinarlib
Version: 0.0.2
Summary: This library simplifies the code
Home-page: https://github.com/ShakhmametovDinar
Author: FORTUNA287
Author-email: shakhmametov1020@gmail.com
License: UNKNOWN
Project-URL: GitHub, https://github.com/ShakhmametovDinar
Keywords: dinar quick_sort intersec
Platform: UNKNOWN
Classifier: Programming Language :: Python :: 3.11
Classifier: License :: OSI Approved :: MIT License
Classifier: Operating System :: OS Independent
Requires-Python: >=3.6
Requires-Dist: requests >=2.25.1
